[
    {
        "run": 14,
        "resolution": 200,
        "population": 2500,
        "scenario_duration": 15,
        "best_individual": "sub(mul(if_then_else(is_water, elevation_v, 0.356), elevation_u), add(distance, sub(steepness, distance)))",
        "best_individual_fitness": [
            3067.0241042524576
        ],
        "hall_of_fame": [
            {
                "individual": "sub(mul(if_then_else(is_water, elevation_v, 0.356), elevation_u), add(distance, sub(steepness, distance)))",
                "fitness": 3067.0241042524576
            },
            {
                "individual": "add(add(distance, 8.565), if_then_else(is_water, sub(add(elevation_v, elevation_u), add(steepness, steepness)), distance))",
                "fitness": 3119.5608933568
            },
            {
                "individual": "add(add(distance, 6.262), if_then_else(identity_water(is_water), sub(add(elevation_v, elevation_u), add(steepness, steepness)), distance))",
                "fitness": 3191.031426951289
            },
            {
                "individual": "add(add(distance, 6.674), if_then_else(identity_water(is_water), sub(add(elevation_v, elevation_u), add(steepness, steepness)), distance))",
                "fitness": 3191.031426951289
            },
            {
                "individual": "add(add(distance, 7.3), if_then_else(identity_water(is_water), sub(add(elevation_v, elevation_u), add(steepness, steepness)), distance))",
                "fitness": 3191.031426951289
            }
        ],
        "runtime_in_seconds": 134.98329734802246
    },
    {
        "run": 14,
        "resolution": 200,
        "population": 2500,
        "scenario_duration": 15,
        "best_individual": "add(if_then_else(is_water, steepness, mul(elevation_v, sub(distance, 0.419))), add(sub(elevation_u, elevation_v), 2.868))",
        "best_individual_fitness": [
            2469.7737902104855
        ],
        "hall_of_fame": [
            {
                "individual": "add(if_then_else(is_water, steepness, mul(elevation_v, sub(distance, 0.419))), add(sub(elevation_u, elevation_v), 2.868))",
                "fitness": 2469.7737902104855
            },
            {
                "individual": "add(if_then_else(identity_water(is_water), steepness, mul(distance, sub(distance, 8.707))), add(sub(elevation_u, elevation_v), 6.87))",
                "fitness": 2497.2736226022243
            },
            {
                "individual": "add(if_then_else(is_water, steepness, mul(distance, sub(distance, 8.707))), add(sub(elevation_u, elevation_v), 6.87))",
                "fitness": 2497.2736226022243
            },
            {
                "individual": "add(if_then_else(identity_water(is_water), steepness, mul(elevation_u, sub(distance, 0.419))), add(sub(elevation_u, elevation_v), 2.868))",
                "fitness": 2535.2419953644276
            },
            {
                "individual": "add(if_then_else(is_water, steepness, mul(elevation_u, sub(distance, 0.419))), add(sub(elevation_u, elevation_v), 2.868))",
                "fitness": 2535.2419953644276
            }
        ],
        "runtime_in_seconds": 124.76579689979553
    }
]