[
    {
        "run": 20,
        "resolution": 200,
        "population": 5000,
        "scenario_duration": 15,
        "best_individual": "add(if_then_else(is_water, sub(distance, elevation_u), distance), mul(add(distance, elevation_v), sub(0.217, steepness)))",
        "best_individual_fitness": [
            54872.1780505024
        ],
        "hall_of_fame": [
            {
                "individual": "add(if_then_else(is_water, sub(distance, elevation_u), distance), mul(add(distance, elevation_v), sub(0.217, steepness)))",
                "fitness": 54872.1780505024
            },
            {
                "individual": "add(if_then_else(is_water, sub(distance, elevation_u), distance), mul(add(distance, elevation_v), sub(0.215, steepness)))",
                "fitness": 54872.19068124718
            },
            {
                "individual": "add(if_then_else(identity_water(is_water), sub(0.232, elevation_u), distance), mul(add(distance, elevation_v), sub(0.232, steepness)))",
                "fitness": 54894.53442029445
            },
            {
                "individual": "add(if_then_else(is_water, sub(0.242, elevation_u), distance), mul(add(distance, elevation_v), sub(0.232, steepness)))",
                "fitness": 54894.53442029445
            },
            {
                "individual": "add(if_then_else(is_water, sub(0.232, elevation_u), distance), mul(add(distance, elevation_v), sub(0.232, steepness)))",
                "fitness": 54894.53442029445
            }
        ],
        "runtime_in_seconds": 5458.795555114746,
        "logs": [
            [
                {
                    "gen": "1.0",
                    "nevals": 5000,
                    "fit_avg": 983800018731.9252,
                    "fit_max": 1000000000000.0,
                    "fit_min": 499835.1672579254,
                    "fit_std": 126243903389.79648
                },
                {
                    "gen": "1.1",
                    "nevals": 2992,
                    "fit_avg": 953600913355.6667,
                    "fit_max": 1000000000000.0,
                    "fit_min": 404834.07964501274,
                    "fit_std": 210345663657.09216
                },
                {
                    "gen": "1.2",
                    "nevals": 2958,
                    "fit_avg": 851604589265.0106,
                    "fit_max": 1000000000000.0,
                    "fit_min": 404769.7644906406,
                    "fit_std": 355485055223.5311
                },
                {
                    "gen": "1.3",
                    "nevals": 2886,
                    "fit_avg": 604815737452.8627,
                    "fit_max": 1000000000000.0,
                    "fit_min": 404574.6277906237,
                    "fit_std": 488874142157.62994
                },
                {
                    "gen": "1.4",
                    "nevals": 3006,
                    "fit_avg": 220028552885.05612,
                    "fit_max": 1000000000000.0,
                    "fit_min": 403857.86214067414,
                    "fit_std": 414231145043.9247
                },
                {
                    "gen": "1.5",
                    "nevals": 3040,
                    "fit_avg": 21421958116.88096,
                    "fit_max": 1000000000000.0,
                    "fit_min": 403821.1438863004,
                    "fit_std": 144710412356.4648
                },
                {
                    "gen": "1.6",
                    "nevals": 3003,
                    "fit_avg": 10417011654.413425,
                    "fit_max": 1000000000000.0,
                    "fit_min": 399872.6688288186,
                    "fit_std": 101446974120.78487
                },
                {
                    "gen": "1.7",
                    "nevals": 3058,
                    "fit_avg": 13218913428.829065,
                    "fit_max": 1000000000000.0,
                    "fit_min": 399872.6688288186,
                    "fit_std": 114128275997.73448
                },
                {
                    "gen": "1.8",
                    "nevals": 3030,
                    "fit_avg": 13218986155.867811,
                    "fit_max": 1000000000000.0,
                    "fit_min": 399837.6987131801,
                    "fit_std": 114128267362.30795
                },
                {
                    "gen": "1.9",
                    "nevals": 2972,
                    "fit_avg": 12617076816.700022,
                    "fit_max": 1000000000000.0,
                    "fit_min": 399837.6987131801,
                    "fit_std": 111538389457.99452
                },
                {
                    "gen": "1.10",
                    "nevals": 2933,
                    "fit_avg": 9217154076.923504,
                    "fit_max": 1000000000000.0,
                    "fit_min": 399827.42016995646,
                    "fit_std": 95472756856.41513
                },
                {
                    "gen": "1.11",
                    "nevals": 3059,
                    "fit_avg": 10615556188.587872,
                    "fit_max": 1000000000000.0,
                    "fit_min": 399827.42016995646,
                    "fit_std": 102407580881.71443
                },
                {
                    "gen": "1.12",
                    "nevals": 2926,
                    "fit_avg": 14213924361.783218,
                    "fit_max": 1000000000000.0,
                    "fit_min": 399584.1855886581,
                    "fit_std": 118313003025.77425
                },
                {
                    "gen": "1.13",
                    "nevals": 3035,
                    "fit_avg": 12215733650.274618,
                    "fit_max": 1000000000000.0,
                    "fit_min": 399771.13051699253,
                    "fit_std": 109776037466.85765
                },
                {
                    "gen": "1.14",
                    "nevals": 3033,
                    "fit_avg": 12015940170.575111,
                    "fit_max": 1000000000000.0,
                    "fit_min": 399584.1855886581,
                    "fit_std": 108883514641.23381
                },
                {
                    "gen": "1.15",
                    "nevals": 3032,
                    "fit_avg": 13815526037.435171,
                    "fit_max": 1000000000000.0,
                    "fit_min": 399584.1855886581,
                    "fit_std": 116658192184.26512
                }
            ],
            [
                {
                    "gen": "2.0",
                    "nevals": 5000,
                    "fit_avg": 13816088057.855465,
                    "fit_max": 1000000000000.0,
                    "fit_min": 584735.8034291723,
                    "fit_std": 116658125655.58836
                },
                {
                    "gen": "2.1",
                    "nevals": 2984,
                    "fit_avg": 12615658713.155926,
                    "fit_max": 1000000000000.0,
                    "fit_min": 584563.5978759471,
                    "fit_std": 111538547534.18204
                },
                {
                    "gen": "2.2",
                    "nevals": 2951,
                    "fit_avg": 9015462707.833523,
                    "fit_max": 1000000000000.0,
                    "fit_min": 584563.5978759471,
                    "fit_std": 94438994967.86978
                },
                {
                    "gen": "2.3",
                    "nevals": 3033,
                    "fit_avg": 9615603931.054502,
                    "fit_max": 1000000000000.0,
                    "fit_min": 584553.3956277493,
                    "fit_std": 97506629094.54788
                },
                {
                    "gen": "2.4",
                    "nevals": 3021,
                    "fit_avg": 11017206179.343002,
                    "fit_max": 1000000000000.0,
                    "fit_min": 215708.04823177366,
                    "fit_std": 104300643002.76921
                },
                {
                    "gen": "2.5",
                    "nevals": 3032,
                    "fit_avg": 7615851765.967916,
                    "fit_max": 1000000000000.0,
                    "fit_min": 215708.04823177366,
                    "fit_std": 86844696430.03745
                },
                {
                    "gen": "2.6",
                    "nevals": 2943,
                    "fit_avg": 10416302366.875832,
                    "fit_max": 1000000000000.0,
                    "fit_min": 215708.04823177366,
                    "fit_std": 101447046928.95746
                },
                {
                    "gen": "2.7",
                    "nevals": 2953,
                    "fit_avg": 8217906116.086808,
                    "fit_max": 1000000000000.0,
                    "fit_min": 215708.04823177366,
                    "fit_std": 90180203696.25955
                },
                {
                    "gen": "2.8",
                    "nevals": 3042,
                    "fit_avg": 9217740118.04646,
                    "fit_max": 1000000000000.0,
                    "fit_min": 215708.04823177366,
                    "fit_std": 95472698925.7659
                },
                {
                    "gen": "2.9",
                    "nevals": 2907,
                    "fit_avg": 10016054491.011843,
                    "fit_max": 1000000000000.0,
                    "fit_min": 215708.04823177366,
                    "fit_std": 99497142811.49615
                },
                {
                    "gen": "2.10",
                    "nevals": 2952,
                    "fit_avg": 9817065315.411474,
                    "fit_max": 1000000000000.0,
                    "fit_min": 215708.04823177366,
                    "fit_std": 98506996040.17586
                },
                {
                    "gen": "2.11",
                    "nevals": 3056,
                    "fit_avg": 8416257973.522711,
                    "fit_max": 1000000000000.0,
                    "fit_min": 215527.9241802475,
                    "fit_std": 91264282866.46104
                },
                {
                    "gen": "2.12",
                    "nevals": 2937,
                    "fit_avg": 8815503135.982443,
                    "fit_max": 1000000000000.0,
                    "fit_min": 214939.76637134547,
                    "fit_std": 93393198441.91393
                },
                {
                    "gen": "2.13",
                    "nevals": 2939,
                    "fit_avg": 7415265688.534825,
                    "fit_max": 1000000000000.0,
                    "fit_min": 214911.7867241672,
                    "fit_std": 85703070291.94597
                },
                {
                    "gen": "2.14",
                    "nevals": 3039,
                    "fit_avg": 8014419423.6552,
                    "fit_max": 1000000000000.0,
                    "fit_min": 214911.7867241672,
                    "fit_std": 89082945956.83296
                },
                {
                    "gen": "2.15",
                    "nevals": 3052,
                    "fit_avg": 9013651858.592268,
                    "fit_max": 1000000000000.0,
                    "fit_min": 214119.23999809485,
                    "fit_std": 94439166669.06479
                }
            ],
            [
                {
                    "gen": "3.0",
                    "nevals": 5000,
                    "fit_avg": 9013794309.551252,
                    "fit_max": 1000000000000.0,
                    "fit_min": 343557.7026882207,
                    "fit_std": 94439153089.84352
                },
                {
                    "gen": "3.1",
                    "nevals": 2920,
                    "fit_avg": 9613473969.187876,
                    "fit_max": 1000000000000.0,
                    "fit_min": 343557.7026882207,
                    "fit_std": 97506836242.77693
                },
                {
                    "gen": "3.2",
                    "nevals": 2982,
                    "fit_avg": 8613514693.937822,
                    "fit_max": 1000000000000.0,
                    "fit_min": 343557.7026882207,
                    "fit_std": 92335309464.44464
                },
                {
                    "gen": "3.3",
                    "nevals": 2985,
                    "fit_avg": 11213695838.672657,
                    "fit_max": 1000000000000.0,
                    "fit_min": 343010.09186517,
                    "fit_std": 105234286646.57156
                },
                {
                    "gen": "3.4",
                    "nevals": 2880,
                    "fit_avg": 8613010390.771925,
                    "fit_max": 1000000000000.0,
                    "fit_min": 343010.09186517,
                    "fit_std": 92335355684.69086
                },
                {
                    "gen": "3.5",
                    "nevals": 3019,
                    "fit_avg": 8214543766.056577,
                    "fit_max": 1000000000000.0,
                    "fit_min": 343010.09186517,
                    "fit_std": 90180504505.71472
                },
                {
                    "gen": "3.6",
                    "nevals": 2951,
                    "fit_avg": 9213793210.405848,
                    "fit_max": 1000000000000.0,
                    "fit_min": 343010.09186517,
                    "fit_std": 95473075345.1388
                },
                {
                    "gen": "3.7",
                    "nevals": 2920,
                    "fit_avg": 10812869959.92047,
                    "fit_max": 1000000000000.0,
                    "fit_min": 343010.09186517,
                    "fit_std": 103359004046.26584
                },
                {
                    "gen": "3.8",
                    "nevals": 3018,
                    "fit_avg": 9413267924.310925,
                    "fit_max": 1000000000000.0,
                    "fit_min": 343010.09186517,
                    "fit_std": 96495556015.2566
                },
                {
                    "gen": "3.9",
                    "nevals": 2879,
                    "fit_avg": 6812736092.046921,
                    "fit_max": 1000000000000.0,
                    "fit_min": 343010.09186517,
                    "fit_std": 82180219925.01959
                },
                {
                    "gen": "3.10",
                    "nevals": 2972,
                    "fit_avg": 8813996062.65695,
                    "fit_max": 1000000000000.0,
                    "fit_min": 343010.09186517,
                    "fit_std": 93393337912.45125
                },
                {
                    "gen": "3.11",
                    "nevals": 2982,
                    "fit_avg": 10814026817.226372,
                    "fit_max": 1000000000000.0,
                    "fit_min": 343010.09186517,
                    "fit_std": 103358884341.67213
                },
                {
                    "gen": "3.12",
                    "nevals": 3035,
                    "fit_avg": 10415425129.656712,
                    "fit_max": 1000000000000.0,
                    "fit_min": 343010.09186517,
                    "fit_std": 101447135148.13023
                },
                {
                    "gen": "3.13",
                    "nevals": 3080,
                    "fit_avg": 9814049573.393213,
                    "fit_max": 1000000000000.0,
                    "fit_min": 343010.09186517,
                    "fit_std": 98507291672.95981
                },
                {
                    "gen": "3.14",
                    "nevals": 2968,
                    "fit_avg": 8412720885.719128,
                    "fit_max": 1000000000000.0,
                    "fit_min": 343010.09186517,
                    "fit_std": 91264603794.54678
                },
                {
                    "gen": "3.15",
                    "nevals": 3057,
                    "fit_avg": 8814713455.425076,
                    "fit_max": 1000000000000.0,
                    "fit_min": 343010.09186517,
                    "fit_std": 93393271370.34718
                }
            ],
            [
                {
                    "gen": "4.0",
                    "nevals": 5000,
                    "fit_avg": 8814818819.11357,
                    "fit_max": 1000000000000.0,
                    "fit_min": 161767.24262307538,
                    "fit_std": 93393261393.50362
                },
                {
                    "gen": "4.1",
                    "nevals": 3014,
                    "fit_avg": 7614834867.724478,
                    "fit_max": 1000000000000.0,
                    "fit_min": 161767.24262307538,
                    "fit_std": 86844783842.70277
                },
                {
                    "gen": "4.2",
                    "nevals": 2980,
                    "fit_avg": 9012640021.29045,
                    "fit_max": 1000000000000.0,
                    "fit_min": 161767.24262307538,
                    "fit_std": 94439261522.17519
                },
                {
                    "gen": "4.3",
                    "nevals": 2958,
                    "fit_avg": 9413350931.919456,
                    "fit_max": 1000000000000.0,
                    "fit_min": 72467.11724707684,
                    "fit_std": 96495547856.81786
                },
                {
                    "gen": "4.4",
                    "nevals": 2982,
                    "fit_avg": 8813385604.136219,
                    "fit_max": 1000000000000.0,
                    "fit_min": 72467.11724707684,
                    "fit_std": 93393395212.38782
                },
                {
                    "gen": "4.5",
                    "nevals": 2992,
                    "fit_avg": 10013148796.38697,
                    "fit_max": 1000000000000.0,
                    "fit_min": 72467.11724707684,
                    "fit_std": 99497430995.58565
                },
                {
                    "gen": "4.6",
                    "nevals": 3062,
                    "fit_avg": 9814026749.464684,
                    "fit_max": 1000000000000.0,
                    "fit_min": 72400.6245203884,
                    "fit_std": 98507293953.71767
                },
                {
                    "gen": "4.7",
                    "nevals": 3142,
                    "fit_avg": 7413713488.280678,
                    "fit_max": 1000000000000.0,
                    "fit_min": 72400.6245203884,
                    "fit_std": 85703202567.0016
                },
                {
                    "gen": "4.8",
                    "nevals": 3030,
                    "fit_avg": 7612932300.407819,
                    "fit_max": 1000000000000.0,
                    "fit_min": 72400.6245203884,
                    "fit_std": 86844948879.33556
                },
                {
                    "gen": "4.9",
                    "nevals": 2998,
                    "fit_avg": 8412795307.001601,
                    "fit_max": 1000000000000.0,
                    "fit_min": 72353.0529254332,
                    "fit_std": 91264597676.98714
                },
                {
                    "gen": "4.10",
                    "nevals": 2986,
                    "fit_avg": 5614061711.187542,
                    "fit_max": 1000000000000.0,
                    "fit_min": 72353.0529254332,
                    "fit_std": 74622278805.4218
                },
                {
                    "gen": "4.11",
                    "nevals": 3088,
                    "fit_avg": 7614701546.226254,
                    "fit_max": 1000000000000.0,
                    "fit_min": 72353.0529254332,
                    "fit_std": 86844795931.7322
                },
                {
                    "gen": "4.12",
                    "nevals": 3008,
                    "fit_avg": 8414520499.191305,
                    "fit_max": 1000000000000.0,
                    "fit_min": 72353.0529254332,
                    "fit_std": 91264440850.42223
                },
                {
                    "gen": "4.13",
                    "nevals": 2952,
                    "fit_avg": 9213676805.14769,
                    "fit_max": 1000000000000.0,
                    "fit_min": 72353.0529254332,
                    "fit_std": 95473087326.00572
                },
                {
                    "gen": "4.14",
                    "nevals": 3025,
                    "fit_avg": 8614572592.992956,
                    "fit_max": 1000000000000.0,
                    "fit_min": 72353.0529254332,
                    "fit_std": 92335213926.92351
                },
                {
                    "gen": "4.15",
                    "nevals": 2975,
                    "fit_avg": 8612848704.924131,
                    "fit_max": 1000000000000.0,
                    "fit_min": 72353.0529254332,
                    "fit_std": 92335372734.64629
                }
            ],
            [
                {
                    "gen": "5.0",
                    "nevals": 5000,
                    "fit_avg": 8613000638.043894,
                    "fit_max": 1000000000000.0,
                    "fit_min": 134191.01833793192,
                    "fit_std": 92335358531.68732
                },
                {
                    "gen": "5.1",
                    "nevals": 2980,
                    "fit_avg": 10414153831.61531,
                    "fit_max": 1000000000000.0,
                    "fit_min": 132970.21247475527,
                    "fit_std": 101447267288.34824
                },
                {
                    "gen": "5.2",
                    "nevals": 2921,
                    "fit_avg": 8013720761.833575,
                    "fit_max": 1000000000000.0,
                    "fit_min": 132970.21247475527,
                    "fit_std": 89083010436.84216
                },
                {
                    "gen": "5.3",
                    "nevals": 2952,
                    "fit_avg": 7814362115.626403,
                    "fit_max": 1000000000000.0,
                    "fit_min": 132970.21247475527,
                    "fit_std": 87971235812.44331
                },
                {
                    "gen": "5.4",
                    "nevals": 3000,
                    "fit_avg": 8013203414.122829,
                    "fit_max": 1000000000000.0,
                    "fit_min": 132970.21247475527,
                    "fit_std": 89083055854.24075
                },
                {
                    "gen": "5.5",
                    "nevals": 2956,
                    "fit_avg": 9813400257.509605,
                    "fit_max": 1000000000000.0,
                    "fit_min": 132970.21247475527,
                    "fit_std": 98507358041.9773
                },
                {
                    "gen": "5.6",
                    "nevals": 3071,
                    "fit_avg": 10215108567.819197,
                    "fit_max": 1000000000000.0,
                    "fit_min": 132970.21247475527,
                    "fit_std": 100477132941.7335
                },
                {
                    "gen": "5.7",
                    "nevals": 2958,
                    "fit_avg": 10014030759.536663,
                    "fit_max": 1000000000000.0,
                    "fit_min": 132970.21247475527,
                    "fit_std": 99497344223.34656
                },
                {
                    "gen": "5.8",
                    "nevals": 3053,
                    "fit_avg": 9614737676.734703,
                    "fit_max": 1000000000000.0,
                    "fit_min": 132970.21247475527,
                    "fit_std": 97506714120.02791
                },
                {
                    "gen": "5.9",
                    "nevals": 3007,
                    "fit_avg": 11813264616.4614,
                    "fit_max": 1000000000000.0,
                    "fit_min": 132520.89127626608,
                    "fit_std": 107983558458.16713
                },
                {
                    "gen": "5.10",
                    "nevals": 3009,
                    "fit_avg": 12215380121.640219,
                    "fit_max": 1000000000000.0,
                    "fit_min": 132968.06153472982,
                    "fit_std": 109776076173.691
                },
                {
                    "gen": "5.11",
                    "nevals": 2952,
                    "fit_avg": 12413914938.175156,
                    "fit_max": 1000000000000.0,
                    "fit_min": 132968.06153472982,
                    "fit_std": 110661180130.49358
                },
                {
                    "gen": "5.12",
                    "nevals": 2989,
                    "fit_avg": 8814232075.660038,
                    "fit_max": 1000000000000.0,
                    "fit_min": 132968.06153472982,
                    "fit_std": 93393316065.66354
                },
                {
                    "gen": "5.13",
                    "nevals": 2980,
                    "fit_avg": 7415301434.023663,
                    "fit_max": 1000000000000.0,
                    "fit_min": 132001.93465027612,
                    "fit_std": 85703066204.81985
                },
                {
                    "gen": "5.14",
                    "nevals": 2980,
                    "fit_avg": 7815982229.589725,
                    "fit_max": 1000000000000.0,
                    "fit_min": 132001.93465027612,
                    "fit_std": 87971091404.77763
                },
                {
                    "gen": "5.15",
                    "nevals": 2931,
                    "fit_avg": 11216485921.188421,
                    "fit_max": 1000000000000.0,
                    "fit_min": 132001.93465027612,
                    "fit_std": 105233992106.61223
                }
            ],
            [
                {
                    "gen": "6.0",
                    "nevals": 5000,
                    "fit_avg": 11217874567.825829,
                    "fit_max": 1000000000000.0,
                    "fit_min": 454635.8960946159,
                    "fit_std": 105233844215.30893
                },
                {
                    "gen": "6.1",
                    "nevals": 2955,
                    "fit_avg": 10217832360.55223,
                    "fit_max": 1000000000000.0,
                    "fit_min": 454635.8960946159,
                    "fit_std": 100476855569.77856
                },
                {
                    "gen": "6.2",
                    "nevals": 2924,
                    "fit_avg": 7415247506.336467,
                    "fit_max": 1000000000000.0,
                    "fit_min": 454635.8960946159,
                    "fit_std": 85703070181.18031
                },
                {
                    "gen": "6.3",
                    "nevals": 2994,
                    "fit_avg": 10216241744.407543,
                    "fit_max": 1000000000000.0,
                    "fit_min": 454635.8960946159,
                    "fit_std": 100477016833.2525
                },
                {
                    "gen": "6.4",
                    "nevals": 2968,
                    "fit_avg": 12016228473.565392,
                    "fit_max": 1000000000000.0,
                    "fit_min": 449781.9168084057,
                    "fit_std": 108883482804.5457
                },
                {
                    "gen": "6.5",
                    "nevals": 3002,
                    "fit_avg": 10816431283.7969,
                    "fit_max": 1000000000000.0,
                    "fit_min": 449781.9168084057,
                    "fit_std": 103358634878.88387
                },
                {
                    "gen": "6.6",
                    "nevals": 3013,
                    "fit_avg": 12016706715.813948,
                    "fit_max": 1000000000000.0,
                    "fit_min": 447506.11690621846,
                    "fit_std": 108883430605.24666
                },
                {
                    "gen": "6.7",
                    "nevals": 2991,
                    "fit_avg": 14018538966.414297,
                    "fit_max": 1000000000000.0,
                    "fit_min": 352074.3135725264,
                    "fit_std": 117488228428.7764
                },
                {
                    "gen": "6.8",
                    "nevals": 3050,
                    "fit_avg": 15218523968.539137,
                    "fit_max": 1000000000000.0,
                    "fit_min": 352074.3135725264,
                    "fit_std": 122345411878.38132
                },
                {
                    "gen": "6.9",
                    "nevals": 2995,
                    "fit_avg": 13618797982.804209,
                    "fit_max": 1000000000000.0,
                    "fit_min": 352074.3135725264,
                    "fit_std": 115821119014.0288
                },
                {
                    "gen": "6.10",
                    "nevals": 2985,
                    "fit_avg": 17216923661.718273,
                    "fit_max": 1000000000000.0,
                    "fit_min": 352074.3135725264,
                    "fit_std": 130013770524.74643
                },
                {
                    "gen": "6.11",
                    "nevals": 2999,
                    "fit_avg": 13213734564.725992,
                    "fit_max": 1000000000000.0,
                    "fit_min": 352074.3135725264,
                    "fit_std": 114128872791.17998
                },
                {
                    "gen": "6.12",
                    "nevals": 2957,
                    "fit_avg": 8013040145.078438,
                    "fit_max": 1000000000000.0,
                    "fit_min": 352074.3135725264,
                    "fit_std": 89083070220.91936
                },
                {
                    "gen": "6.13",
                    "nevals": 2925,
                    "fit_avg": 9413850390.227015,
                    "fit_max": 1000000000000.0,
                    "fit_min": 352074.3135725264,
                    "fit_std": 96495501172.86366
                },
                {
                    "gen": "6.14",
                    "nevals": 3007,
                    "fit_avg": 8014929885.737324,
                    "fit_max": 1000000000000.0,
                    "fit_min": 352074.3135725264,
                    "fit_std": 89082901367.62357
                },
                {
                    "gen": "6.15",
                    "nevals": 3044,
                    "fit_avg": 7215742243.732759,
                    "fit_max": 1000000000000.0,
                    "fit_min": 352074.3135725264,
                    "fit_std": 84545465572.52559
                }
            ],
            [
                {
                    "gen": "7.0",
                    "nevals": 5000,
                    "fit_avg": 7215945289.548444,
                    "fit_max": 1000000000000.0,
                    "fit_min": 65010.747058896486,
                    "fit_std": 84545448231.97893
                },
                {
                    "gen": "7.1",
                    "nevals": 3020,
                    "fit_avg": 8814469053.891413,
                    "fit_max": 1000000000000.0,
                    "fit_min": 64995.64390754347,
                    "fit_std": 93393294912.84575
                },
                {
                    "gen": "7.2",
                    "nevals": 2970,
                    "fit_avg": 9214285357.841793,
                    "fit_max": 1000000000000.0,
                    "fit_min": 64562.18619198984,
                    "fit_std": 95473029395.76984
                },
                {
                    "gen": "7.3",
                    "nevals": 3010,
                    "fit_avg": 8614965456.904415,
                    "fit_max": 1000000000000.0,
                    "fit_min": 64380.84282492904,
                    "fit_std": 92335177132.93729
                },
                {
                    "gen": "7.4",
                    "nevals": 3048,
                    "fit_avg": 10814118654.692024,
                    "fit_max": 1000000000000.0,
                    "fit_min": 64380.84153151189,
                    "fit_std": 103358875985.6662
                },
                {
                    "gen": "7.5",
                    "nevals": 3005,
                    "fit_avg": 10814864987.842182,
                    "fit_max": 1000000000000.0,
                    "fit_min": 64380.84153151189,
                    "fit_std": 103358797465.12195
                },
                {
                    "gen": "7.6",
                    "nevals": 2903,
                    "fit_avg": 9815357015.326622,
                    "fit_max": 1000000000000.0,
                    "fit_min": 64309.92401631667,
                    "fit_std": 98507163644.48169
                },
                {
                    "gen": "7.7",
                    "nevals": 2972,
                    "fit_avg": 8816149218.632113,
                    "fit_max": 1000000000000.0,
                    "fit_min": 64309.92401631667,
                    "fit_std": 93393137525.27696
                },
                {
                    "gen": "7.8",
                    "nevals": 2953,
                    "fit_avg": 7016388019.892109,
                    "fit_max": 1000000000000.0,
                    "fit_min": 64146.792252946674,
                    "fit_std": 83371296700.45576
                },
                {
                    "gen": "7.9",
                    "nevals": 2933,
                    "fit_avg": 10416794724.238693,
                    "fit_max": 1000000000000.0,
                    "fit_min": 64146.792252946674,
                    "fit_std": 101446997236.4278
                },
                {
                    "gen": "7.10",
                    "nevals": 3027,
                    "fit_avg": 9416193163.974918,
                    "fit_max": 1000000000000.0,
                    "fit_min": 64146.792252946674,
                    "fit_std": 96495275612.50067
                },
                {
                    "gen": "7.11",
                    "nevals": 2975,
                    "fit_avg": 13016353698.33223,
                    "fit_max": 1000000000000.0,
                    "fit_min": 64146.792252946674,
                    "fit_std": 113272138668.44295
                },
                {
                    "gen": "7.12",
                    "nevals": 3014,
                    "fit_avg": 10615080388.922415,
                    "fit_max": 1000000000000.0,
                    "fit_min": 64146.792252946674,
                    "fit_std": 102407630875.67293
                },
                {
                    "gen": "7.13",
                    "nevals": 2962,
                    "fit_avg": 7614200853.089225,
                    "fit_max": 1000000000000.0,
                    "fit_min": 64146.792252946674,
                    "fit_std": 86844842338.95203
                },
                {
                    "gen": "7.14",
                    "nevals": 2984,
                    "fit_avg": 8615057863.822556,
                    "fit_max": 1000000000000.0,
                    "fit_min": 64146.792252946674,
                    "fit_std": 92335169553.29826
                },
                {
                    "gen": "7.15",
                    "nevals": 2939,
                    "fit_avg": 6614974111.142737,
                    "fit_max": 1000000000000.0,
                    "fit_min": 64146.792252946674,
                    "fit_std": 80970642117.8735
                }
            ],
            [
                {
                    "gen": "8.0",
                    "nevals": 5000,
                    "fit_avg": 6616453619.950108,
                    "fit_max": 1000000000000.0,
                    "fit_min": 884438.3115456683,
                    "fit_std": 80970521453.50314
                },
                {
                    "gen": "8.1",
                    "nevals": 3042,
                    "fit_avg": 8815996352.60912,
                    "fit_max": 1000000000000.0,
                    "fit_min": 232469.8569381796,
                    "fit_std": 93393151448.35678
                },
                {
                    "gen": "8.2",
                    "nevals": 3004,
                    "fit_avg": 8816198067.653318,
                    "fit_max": 1000000000000.0,
                    "fit_min": 167283.82432664963,
                    "fit_std": 93393132999.67694
                },
                {
                    "gen": "8.3",
                    "nevals": 3023,
                    "fit_avg": 7616261105.395658,
                    "fit_max": 1000000000000.0,
                    "fit_min": 167283.82432664963,
                    "fit_std": 86844661423.48795
                },
                {
                    "gen": "8.4",
                    "nevals": 3054,
                    "fit_avg": 9616987375.779646,
                    "fit_max": 1000000000000.0,
                    "fit_min": 167283.82432664963,
                    "fit_std": 97506494277.69334
                },
                {
                    "gen": "8.5",
                    "nevals": 3123,
                    "fit_avg": 10217994303.30153,
                    "fit_max": 1000000000000.0,
                    "fit_min": 159693.5374868915,
                    "fit_std": 100476841414.56961
                },
                {
                    "gen": "8.6",
                    "nevals": 2947,
                    "fit_avg": 8417175689.767172,
                    "fit_max": 1000000000000.0,
                    "fit_min": 159514.9739414183,
                    "fit_std": 91264199431.02547
                },
                {
                    "gen": "8.7",
                    "nevals": 2998,
                    "fit_avg": 10818492742.146038,
                    "fit_max": 1000000000000.0,
                    "fit_min": 159514.9739414183,
                    "fit_std": 103358421844.71358
                },
                {
                    "gen": "8.8",
                    "nevals": 2972,
                    "fit_avg": 11619634356.211206,
                    "fit_max": 1000000000000.0,
                    "fit_min": 159445.9363603763,
                    "fit_std": 107074681536.73703
                },
                {
                    "gen": "8.9",
                    "nevals": 3012,
                    "fit_avg": 11218499970.429142,
                    "fit_max": 1000000000000.0,
                    "fit_min": 159445.9363603763,
                    "fit_std": 105233779558.5733
                },
                {
                    "gen": "8.10",
                    "nevals": 2988,
                    "fit_avg": 7617590695.830075,
                    "fit_max": 1000000000000.0,
                    "fit_min": 159445.9363603763,
                    "fit_std": 86844547004.98819
                },
                {
                    "gen": "8.11",
                    "nevals": 2988,
                    "fit_avg": 8216159995.47704,
                    "fit_max": 1000000000000.0,
                    "fit_min": 159445.9363603763,
                    "fit_std": 90180360837.72902
                },
                {
                    "gen": "8.12",
                    "nevals": 3004,
                    "fit_avg": 10215902930.039116,
                    "fit_max": 1000000000000.0,
                    "fit_min": 159445.9363603763,
                    "fit_std": 100477052722.85976
                },
                {
                    "gen": "8.13",
                    "nevals": 2945,
                    "fit_avg": 7414969581.022251,
                    "fit_max": 1000000000000.0,
                    "fit_min": 159445.9363603763,
                    "fit_std": 85703096717.91808
                },
                {
                    "gen": "8.14",
                    "nevals": 2937,
                    "fit_avg": 9615752402.8303,
                    "fit_max": 1000000000000.0,
                    "fit_min": 159445.92215716146,
                    "fit_std": 97506615512.24445
                },
                {
                    "gen": "8.15",
                    "nevals": 3035,
                    "fit_avg": 8016385586.434144,
                    "fit_max": 1000000000000.0,
                    "fit_min": 159445.92215716146,
                    "fit_std": 89082772642.46562
                }
            ],
            [
                {
                    "gen": "9.0",
                    "nevals": 5000,
                    "fit_avg": 8016962640.639565,
                    "fit_max": 1000000000000.0,
                    "fit_min": 370363.7158738824,
                    "fit_std": 89082720603.11395
                },
                {
                    "gen": "9.1",
                    "nevals": 2984,
                    "fit_avg": 9016170996.00391,
                    "fit_max": 1000000000000.0,
                    "fit_min": 370363.7158738824,
                    "fit_std": 94438929822.85008
                },
                {
                    "gen": "9.2",
                    "nevals": 3042,
                    "fit_avg": 7416227578.230478,
                    "fit_max": 1000000000000.0,
                    "fit_min": 370363.7158738824,
                    "fit_std": 85702988487.61993
                },
                {
                    "gen": "9.3",
                    "nevals": 3010,
                    "fit_avg": 9214343574.006962,
                    "fit_max": 1000000000000.0,
                    "fit_min": 370363.7158738824,
                    "fit_std": 95473024070.72388
                },
                {
                    "gen": "9.4",
                    "nevals": 2995,
                    "fit_avg": 10214586692.017862,
                    "fit_max": 1000000000000.0,
                    "fit_min": 370363.7158738824,
                    "fit_std": 100477184478.90587
                },
                {
                    "gen": "9.5",
                    "nevals": 2997,
                    "fit_avg": 9614837891.07539,
                    "fit_max": 1000000000000.0,
                    "fit_min": 370363.7158738824,
                    "fit_std": 97506705223.09987
                },
                {
                    "gen": "9.6",
                    "nevals": 3018,
                    "fit_avg": 7615356627.110082,
                    "fit_max": 1000000000000.0,
                    "fit_min": 370363.7158738824,
                    "fit_std": 86844741820.20569
                },
                {
                    "gen": "9.7",
                    "nevals": 3097,
                    "fit_avg": 11013089471.460335,
                    "fit_max": 1000000000000.0,
                    "fit_min": 370363.7158738824,
                    "fit_std": 104301073972.93259
                },
                {
                    "gen": "9.8",
                    "nevals": 3005,
                    "fit_avg": 8814102285.592806,
                    "fit_max": 1000000000000.0,
                    "fit_min": 370363.7158738824,
                    "fit_std": 93393330515.38498
                },
                {
                    "gen": "9.9",
                    "nevals": 3094,
                    "fit_avg": 8814736586.800993,
                    "fit_max": 1000000000000.0,
                    "fit_min": 370363.7087727714,
                    "fit_std": 93393270653.59253
                },
                {
                    "gen": "9.10",
                    "nevals": 3014,
                    "fit_avg": 9413818654.284746,
                    "fit_max": 1000000000000.0,
                    "fit_min": 370363.7087727714,
                    "fit_std": 96495505117.55013
                },
                {
                    "gen": "9.11",
                    "nevals": 3023,
                    "fit_avg": 7414041367.346967,
                    "fit_max": 1000000000000.0,
                    "fit_min": 370363.7087727714,
                    "fit_std": 85703176470.87016
                },
                {
                    "gen": "9.12",
                    "nevals": 2959,
                    "fit_avg": 9013553514.714903,
                    "fit_max": 1000000000000.0,
                    "fit_min": 370363.7087727714,
                    "fit_std": 94439177693.27812
                },
                {
                    "gen": "9.13",
                    "nevals": 2998,
                    "fit_avg": 7012783663.693325,
                    "fit_max": 1000000000000.0,
                    "fit_min": 370363.7087727714,
                    "fit_std": 83371596463.82762
                },
                {
                    "gen": "9.14",
                    "nevals": 3038,
                    "fit_avg": 10613093516.419556,
                    "fit_max": 1000000000000.0,
                    "fit_min": 370363.7087727714,
                    "fit_std": 102407833831.97441
                },
                {
                    "gen": "9.15",
                    "nevals": 3080,
                    "fit_avg": 8013854968.960697,
                    "fit_max": 1000000000000.0,
                    "fit_min": 370363.7087727714,
                    "fit_std": 89082997936.89833
                }
            ],
            [
                {
                    "gen": "10.0",
                    "nevals": 5000,
                    "fit_avg": 8014154241.920201,
                    "fit_max": 1000000000000.0,
                    "fit_min": 96401.79317709911,
                    "fit_std": 89082971048.04922
                },
                {
                    "gen": "10.1",
                    "nevals": 2930,
                    "fit_avg": 8013002580.013903,
                    "fit_max": 1000000000000.0,
                    "fit_min": 96401.79317709911,
                    "fit_std": 89083072957.56319
                },
                {
                    "gen": "10.2",
                    "nevals": 3025,
                    "fit_avg": 10013646669.215332,
                    "fit_max": 1000000000000.0,
                    "fit_min": 96401.79317709911,
                    "fit_std": 99497382373.86519
                },
                {
                    "gen": "10.3",
                    "nevals": 3091,
                    "fit_avg": 9214445721.821604,
                    "fit_max": 1000000000000.0,
                    "fit_min": 96401.79317709911,
                    "fit_std": 95473014481.10103
                },
                {
                    "gen": "10.4",
                    "nevals": 3048,
                    "fit_avg": 8214849160.242413,
                    "fit_max": 1000000000000.0,
                    "fit_min": 95843.42215804578,
                    "fit_std": 90180478196.87404
                },
                {
                    "gen": "10.5",
                    "nevals": 2990,
                    "fit_avg": 11213761851.86644,
                    "fit_max": 1000000000000.0,
                    "fit_min": 96401.79317709911,
                    "fit_std": 105234280850.77864
                },
                {
                    "gen": "10.6",
                    "nevals": 2986,
                    "fit_avg": 9414455687.743803,
                    "fit_max": 1000000000000.0,
                    "fit_min": 96401.79317709911,
                    "fit_std": 96495442149.88593
                },
                {
                    "gen": "10.7",
                    "nevals": 3059,
                    "fit_avg": 9214690009.782005,
                    "fit_max": 1000000000000.0,
                    "fit_min": 96132.64547830712,
                    "fit_std": 95472990104.14153
                },
                {
                    "gen": "10.8",
                    "nevals": 2953,
                    "fit_avg": 8013464522.988807,
                    "fit_max": 1000000000000.0,
                    "fit_min": 96132.64547830712,
                    "fit_std": 89083030978.07095
                },
                {
                    "gen": "10.9",
                    "nevals": 2974,
                    "fit_avg": 8812469258.523752,
                    "fit_max": 1000000000000.0,
                    "fit_min": 96132.64547830712,
                    "fit_std": 93393480503.72414
                },
                {
                    "gen": "10.10",
                    "nevals": 3002,
                    "fit_avg": 10412690367.763014,
                    "fit_max": 1000000000000.0,
                    "fit_min": 94996.96853930758,
                    "fit_std": 101447414063.77641
                },
                {
                    "gen": "10.11",
                    "nevals": 2942,
                    "fit_avg": 9413142598.459776,
                    "fit_max": 1000000000000.0,
                    "fit_min": 94996.96853930758,
                    "fit_std": 96495568128.60912
                },
                {
                    "gen": "10.12",
                    "nevals": 3043,
                    "fit_avg": 7613640394.191125,
                    "fit_max": 1000000000000.0,
                    "fit_min": 94981.84360665805,
                    "fit_std": 86844887160.77794
                },
                {
                    "gen": "10.13",
                    "nevals": 2993,
                    "fit_avg": 8615554647.040071,
                    "fit_max": 1000000000000.0,
                    "fit_min": 94981.84360665805,
                    "fit_std": 92335120669.38321
                },
                {
                    "gen": "10.14",
                    "nevals": 3041,
                    "fit_avg": 9016138934.496065,
                    "fit_max": 1000000000000.0,
                    "fit_min": 94815.45037594553,
                    "fit_std": 94438931249.67056
                },
                {
                    "gen": "10.15",
                    "nevals": 3065,
                    "fit_avg": 10415767661.585922,
                    "fit_max": 1000000000000.0,
                    "fit_min": 94436.55524093218,
                    "fit_std": 101447100827.86768
                }
            ],
            [
                {
                    "gen": "11.0",
                    "nevals": 5000,
                    "fit_avg": 10415982317.668411,
                    "fit_max": 1000000000000.0,
                    "fit_min": 275409.6527978352,
                    "fit_std": 101447078734.33469
                },
                {
                    "gen": "11.1",
                    "nevals": 3012,
                    "fit_avg": 8614726038.19364,
                    "fit_max": 1000000000000.0,
                    "fit_min": 275409.6527978352,
                    "fit_std": 92335196660.16129
                },
                {
                    "gen": "11.2",
                    "nevals": 3045,
                    "fit_avg": 7815203427.006175,
                    "fit_max": 1000000000000.0,
                    "fit_min": 275409.6527978352,
                    "fit_std": 87971158646.0287
                },
                {
                    "gen": "11.3",
                    "nevals": 3011,
                    "fit_avg": 10215296952.968922,
                    "fit_max": 1000000000000.0,
                    "fit_min": 275378.3153448081,
                    "fit_std": 100477111134.72562
                },
                {
                    "gen": "11.4",
                    "nevals": 3041,
                    "fit_avg": 9414983059.496672,
                    "fit_max": 1000000000000.0,
                    "fit_min": 275378.3153448081,
                    "fit_std": 96495389320.92625
                },
                {
                    "gen": "11.5",
                    "nevals": 3034,
                    "fit_avg": 9414773530.403835,
                    "fit_max": 1000000000000.0,
                    "fit_min": 275378.3153448081,
                    "fit_std": 96495410145.35709
                },
                {
                    "gen": "11.6",
                    "nevals": 3027,
                    "fit_avg": 9416185460.08958,
                    "fit_max": 1000000000000.0,
                    "fit_min": 275378.3153448081,
                    "fit_std": 96495274318.68622
                },
                {
                    "gen": "11.7",
                    "nevals": 2970,
                    "fit_avg": 10215180694.75945,
                    "fit_max": 1000000000000.0,
                    "fit_min": 275351.4128512259,
                    "fit_std": 100477123708.40862
                },
                {
                    "gen": "11.8",
                    "nevals": 2937,
                    "fit_avg": 8616592901.390257,
                    "fit_max": 1000000000000.0,
                    "fit_min": 275351.4128512259,
                    "fit_std": 92335025549.59396
                },
                {
                    "gen": "11.9",
                    "nevals": 2966,
                    "fit_avg": 10215747078.911058,
                    "fit_max": 1000000000000.0,
                    "fit_min": 275131.21266178455,
                    "fit_std": 100477068046.35948
                },
                {
                    "gen": "11.10",
                    "nevals": 2995,
                    "fit_avg": 11416049226.475288,
                    "fit_max": 1000000000000.0,
                    "fit_min": 275131.21266178455,
                    "fit_std": 106158732573.45078
                },
                {
                    "gen": "11.11",
                    "nevals": 3026,
                    "fit_avg": 9216704030.638935,
                    "fit_max": 1000000000000.0,
                    "fit_min": 275131.21266178455,
                    "fit_std": 95472798314.65027
                },
                {
                    "gen": "11.12",
                    "nevals": 3028,
                    "fit_avg": 9015907726.070168,
                    "fit_max": 1000000000000.0,
                    "fit_min": 275131.21266178455,
                    "fit_std": 94438953835.14795
                },
                {
                    "gen": "11.13",
                    "nevals": 3053,
                    "fit_avg": 7615361630.052075,
                    "fit_max": 1000000000000.0,
                    "fit_min": 275131.21025116503,
                    "fit_std": 86844739881.94696
                },
                {
                    "gen": "11.14",
                    "nevals": 2920,
                    "fit_avg": 9213861576.597834,
                    "fit_max": 1000000000000.0,
                    "fit_min": 275131.21025116503,
                    "fit_std": 95473070325.54227
                },
                {
                    "gen": "11.15",
                    "nevals": 3052,
                    "fit_avg": 9614321894.216627,
                    "fit_max": 1000000000000.0,
                    "fit_min": 275131.21025116503,
                    "fit_std": 97506755417.36092
                }
            ],
            [
                {
                    "gen": "12.0",
                    "nevals": 5000,
                    "fit_avg": 9614312960.600357,
                    "fit_max": 1000000000000.0,
                    "fit_min": 191576.89475285658,
                    "fit_std": 97506756301.75781
                },
                {
                    "gen": "12.1",
                    "nevals": 2976,
                    "fit_avg": 6013757439.209692,
                    "fit_max": 1000000000000.0,
                    "fit_min": 191576.89475285658,
                    "fit_std": 77225883528.16191
                },
                {
                    "gen": "12.2",
                    "nevals": 3030,
                    "fit_avg": 9614238827.020657,
                    "fit_max": 1000000000000.0,
                    "fit_min": 191576.89475285658,
                    "fit_std": 97506762738.41446
                },
                {
                    "gen": "12.3",
                    "nevals": 2951,
                    "fit_avg": 8215014845.479086,
                    "fit_max": 1000000000000.0,
                    "fit_min": 191576.89475285658,
                    "fit_std": 90180464320.80762
                },
                {
                    "gen": "12.4",
                    "nevals": 2955,
                    "fit_avg": 9614553382.092855,
                    "fit_max": 1000000000000.0,
                    "fit_min": 191576.89475285658,
                    "fit_std": 97506732339.12433
                },
                {
                    "gen": "12.5",
                    "nevals": 3003,
                    "fit_avg": 9414687179.817455,
                    "fit_max": 1000000000000.0,
                    "fit_min": 134543.46336042922,
                    "fit_std": 96495421088.15796
                },
                {
                    "gen": "12.6",
                    "nevals": 3023,
                    "fit_avg": 6814965702.621599,
                    "fit_max": 1000000000000.0,
                    "fit_min": 134543.46336042922,
                    "fit_std": 82180038942.61058
                },
                {
                    "gen": "12.7",
                    "nevals": 2967,
                    "fit_avg": 6815443466.877062,
                    "fit_max": 1000000000000.0,
                    "fit_min": 134543.46336042922,
                    "fit_std": 82179999933.80513
                },
                {
                    "gen": "12.8",
                    "nevals": 3025,
                    "fit_avg": 9016205833.274532,
                    "fit_max": 1000000000000.0,
                    "fit_min": 134543.46336042922,
                    "fit_std": 94438927015.60472
                },
                {
                    "gen": "12.9",
                    "nevals": 3015,
                    "fit_avg": 8614396631.55725,
                    "fit_max": 1000000000000.0,
                    "fit_min": 133192.9294257986,
                    "fit_std": 92335229860.93298
                },
                {
                    "gen": "12.10",
                    "nevals": 2998,
                    "fit_avg": 8614319146.843163,
                    "fit_max": 1000000000000.0,
                    "fit_min": 133192.9294257986,
                    "fit_std": 92335236951.58318
                },
                {
                    "gen": "12.11",
                    "nevals": 3045,
                    "fit_avg": 8215023954.98227,
                    "fit_max": 1000000000000.0,
                    "fit_min": 133192.9294257986,
                    "fit_std": 90180463422.67366
                },
                {
                    "gen": "12.12",
                    "nevals": 2909,
                    "fit_avg": 9613464210.088871,
                    "fit_max": 1000000000000.0,
                    "fit_min": 133192.9294257986,
                    "fit_std": 97506838061.8649
                },
                {
                    "gen": "12.13",
                    "nevals": 3070,
                    "fit_avg": 7615318923.513887,
                    "fit_max": 1000000000000.0,
                    "fit_min": 133192.9294257986,
                    "fit_std": 86844744789.22043
                },
                {
                    "gen": "12.14",
                    "nevals": 2998,
                    "fit_avg": 7613795987.270672,
                    "fit_max": 1000000000000.0,
                    "fit_min": 131784.44078539533,
                    "fit_std": 86844875821.39253
                },
                {
                    "gen": "12.15",
                    "nevals": 2975,
                    "fit_avg": 7213888391.552348,
                    "fit_max": 1000000000000.0,
                    "fit_min": 131784.44078539533,
                    "fit_std": 84545622109.40872
                }
            ],
            [
                {
                    "gen": "13.0",
                    "nevals": 5000,
                    "fit_avg": 7214030798.585309,
                    "fit_max": 1000000000000.0,
                    "fit_min": 100539.85923873099,
                    "fit_std": 84545609944.03618
                },
                {
                    "gen": "13.1",
                    "nevals": 3063,
                    "fit_avg": 8614326435.615292,
                    "fit_max": 1000000000000.0,
                    "fit_min": 100519.37541841876,
                    "fit_std": 92335236210.36526
                },
                {
                    "gen": "13.2",
                    "nevals": 2978,
                    "fit_avg": 7414631019.165179,
                    "fit_max": 1000000000000.0,
                    "fit_min": 100395.11506925315,
                    "fit_std": 85703125757.64084
                },
                {
                    "gen": "13.3",
                    "nevals": 3007,
                    "fit_avg": 7215303072.002728,
                    "fit_max": 1000000000000.0,
                    "fit_min": 100395.11506925315,
                    "fit_std": 84545502541.96085
                },
                {
                    "gen": "13.4",
                    "nevals": 3015,
                    "fit_avg": 10014932842.4761,
                    "fit_max": 1000000000000.0,
                    "fit_min": 100395.11506925315,
                    "fit_std": 99497254733.08855
                },
                {
                    "gen": "13.5",
                    "nevals": 3019,
                    "fit_avg": 8815206490.266804,
                    "fit_max": 1000000000000.0,
                    "fit_min": 100395.11506925315,
                    "fit_std": 93393226021.14722
                },
                {
                    "gen": "13.6",
                    "nevals": 3079,
                    "fit_avg": 9214921413.01818,
                    "fit_max": 1000000000000.0,
                    "fit_min": 100395.11506925315,
                    "fit_std": 95472967766.77151
                },
                {
                    "gen": "13.7",
                    "nevals": 2926,
                    "fit_avg": 8813914450.491652,
                    "fit_max": 1000000000000.0,
                    "fit_min": 100395.11506925315,
                    "fit_std": 93393345833.54811
                },
                {
                    "gen": "13.8",
                    "nevals": 3017,
                    "fit_avg": 7215207112.404394,
                    "fit_max": 1000000000000.0,
                    "fit_min": 100395.11506925315,
                    "fit_std": 84545508609.65056
                },
                {
                    "gen": "13.9",
                    "nevals": 3020,
                    "fit_avg": 8415542962.7884655,
                    "fit_max": 1000000000000.0,
                    "fit_min": 100395.11506925315,
                    "fit_std": 91264346102.89388
                },
                {
                    "gen": "13.10",
                    "nevals": 3002,
                    "fit_avg": 10413152795.882788,
                    "fit_max": 1000000000000.0,
                    "fit_min": 100395.11506925315,
                    "fit_std": 101447366443.09111
                },
                {
                    "gen": "13.11",
                    "nevals": 3046,
                    "fit_avg": 7615916804.607821,
                    "fit_max": 1000000000000.0,
                    "fit_min": 100395.11506925315,
                    "fit_std": 86844689451.37651
                },
                {
                    "gen": "13.12",
                    "nevals": 2874,
                    "fit_avg": 10013967428.049603,
                    "fit_max": 1000000000000.0,
                    "fit_min": 100395.11506925315,
                    "fit_std": 99497348928.10442
                },
                {
                    "gen": "13.13",
                    "nevals": 3054,
                    "fit_avg": 8415704425.910971,
                    "fit_max": 1000000000000.0,
                    "fit_min": 100395.11506925315,
                    "fit_std": 91264331349.79498
                },
                {
                    "gen": "13.14",
                    "nevals": 2957,
                    "fit_avg": 6415186274.276919,
                    "fit_max": 1000000000000.0,
                    "fit_min": 100395.11506925315,
                    "fit_std": 79742382551.53343
                },
                {
                    "gen": "13.15",
                    "nevals": 2966,
                    "fit_avg": 9613665359.181057,
                    "fit_max": 1000000000000.0,
                    "fit_min": 100395.11506925315,
                    "fit_std": 97506816846.9696
                }
            ],
            [
                {
                    "gen": "14.0",
                    "nevals": 5000,
                    "fit_avg": 9613954856.796791,
                    "fit_max": 1000000000000.0,
                    "fit_min": 107697.49042366084,
                    "fit_std": 97506788321.82034
                },
                {
                    "gen": "14.1",
                    "nevals": 2992,
                    "fit_avg": 11014100291.180494,
                    "fit_max": 1000000000000.0,
                    "fit_min": 107697.49042366084,
                    "fit_std": 104300965965.09035
                },
                {
                    "gen": "14.2",
                    "nevals": 2999,
                    "fit_avg": 9815253848.37402,
                    "fit_max": 1000000000000.0,
                    "fit_min": 107697.49042366084,
                    "fit_std": 98507172062.39624
                },
                {
                    "gen": "14.3",
                    "nevals": 2968,
                    "fit_avg": 8214446564.69729,
                    "fit_max": 1000000000000.0,
                    "fit_min": 107697.49042366084,
                    "fit_std": 90180513008.35304
                },
                {
                    "gen": "14.4",
                    "nevals": 3062,
                    "fit_avg": 7015450442.188847,
                    "fit_max": 1000000000000.0,
                    "fit_min": 107575.369110636,
                    "fit_std": 83371372139.7091
                },
                {
                    "gen": "14.5",
                    "nevals": 2999,
                    "fit_avg": 9814898879.865515,
                    "fit_max": 1000000000000.0,
                    "fit_min": 107575.369110636,
                    "fit_std": 98507207958.49146
                },
                {
                    "gen": "14.6",
                    "nevals": 2991,
                    "fit_avg": 9615064396.525244,
                    "fit_max": 1000000000000.0,
                    "fit_min": 107575.369110636,
                    "fit_std": 97506681305.4917
                },
                {
                    "gen": "14.7",
                    "nevals": 2993,
                    "fit_avg": 8213876393.724475,
                    "fit_max": 1000000000000.0,
                    "fit_min": 107575.369110636,
                    "fit_std": 90180565670.20436
                },
                {
                    "gen": "14.8",
                    "nevals": 2989,
                    "fit_avg": 8415933073.920553,
                    "fit_max": 1000000000000.0,
                    "fit_min": 107567.4866016333,
                    "fit_std": 91264310898.5135
                },
                {
                    "gen": "14.9",
                    "nevals": 3064,
                    "fit_avg": 7216763202.492833,
                    "fit_max": 1000000000000.0,
                    "fit_min": 107567.4866016333,
                    "fit_std": 84545377401.05759
                },
                {
                    "gen": "14.10",
                    "nevals": 2980,
                    "fit_avg": 10615341003.50615,
                    "fit_max": 1000000000000.0,
                    "fit_min": 107567.4866016333,
                    "fit_std": 102407600713.37183
                },
                {
                    "gen": "14.11",
                    "nevals": 3031,
                    "fit_avg": 8014658576.666234,
                    "fit_max": 1000000000000.0,
                    "fit_min": 107575.369110636,
                    "fit_std": 89082924157.33846
                },
                {
                    "gen": "14.12",
                    "nevals": 3041,
                    "fit_avg": 9614658445.089346,
                    "fit_max": 1000000000000.0,
                    "fit_min": 107575.369110636,
                    "fit_std": 97506719992.8698
                },
                {
                    "gen": "14.13",
                    "nevals": 2986,
                    "fit_avg": 7814054451.625806,
                    "fit_max": 1000000000000.0,
                    "fit_min": 107575.369110636,
                    "fit_std": 87971259608.40523
                },
                {
                    "gen": "14.14",
                    "nevals": 2969,
                    "fit_avg": 7814278729.458859,
                    "fit_max": 1000000000000.0,
                    "fit_min": 107575.369110636,
                    "fit_std": 87971240335.75758
                },
                {
                    "gen": "14.15",
                    "nevals": 2960,
                    "fit_avg": 9613660518.467775,
                    "fit_max": 1000000000000.0,
                    "fit_min": 107575.369110636,
                    "fit_std": 97506817544.1382
                }
            ],
            [
                {
                    "gen": "15.0",
                    "nevals": 5000,
                    "fit_avg": 9614979564.761524,
                    "fit_max": 1000000000000.0,
                    "fit_min": 54988.89845326262,
                    "fit_std": 97506687565.54678
                },
                {
                    "gen": "15.1",
                    "nevals": 2978,
                    "fit_avg": 8014971931.678378,
                    "fit_max": 1000000000000.0,
                    "fit_min": 54988.89845326262,
                    "fit_std": 89082895146.18085
                },
                {
                    "gen": "15.2",
                    "nevals": 3014,
                    "fit_avg": 8414876320.667853,
                    "fit_max": 1000000000000.0,
                    "fit_min": 54894.53887269891,
                    "fit_std": 91264406152.87029
                },
                {
                    "gen": "15.3",
                    "nevals": 2962,
                    "fit_avg": 9614626468.772085,
                    "fit_max": 1000000000000.0,
                    "fit_min": 54894.53887269891,
                    "fit_std": 97506722488.50171
                },
                {
                    "gen": "15.4",
                    "nevals": 2959,
                    "fit_avg": 10814528194.562912,
                    "fit_max": 1000000000000.0,
                    "fit_min": 54894.53887269891,
                    "fit_std": 103358831241.41881
                },
                {
                    "gen": "15.5",
                    "nevals": 3029,
                    "fit_avg": 10015092413.75202,
                    "fit_max": 1000000000000.0,
                    "fit_min": 54894.53887269891,
                    "fit_std": 99497236747.62685
                },
                {
                    "gen": "15.6",
                    "nevals": 2987,
                    "fit_avg": 8414752561.855048,
                    "fit_max": 1000000000000.0,
                    "fit_min": 54894.53887269891,
                    "fit_std": 91264418964.5682
                },
                {
                    "gen": "15.7",
                    "nevals": 2922,
                    "fit_avg": 12815309834.81126,
                    "fit_max": 1000000000000.0,
                    "fit_min": 54894.53887269891,
                    "fit_std": 112408942538.15755
                },
                {
                    "gen": "15.8",
                    "nevals": 3063,
                    "fit_avg": 11017190635.672562,
                    "fit_max": 1000000000000.0,
                    "fit_min": 54894.53887269891,
                    "fit_std": 104300644260.45757
                },
                {
                    "gen": "15.9",
                    "nevals": 2999,
                    "fit_avg": 9616331542.292582,
                    "fit_max": 1000000000000.0,
                    "fit_min": 54894.53887269891,
                    "fit_std": 97506556903.30545
                },
                {
                    "gen": "15.10",
                    "nevals": 2972,
                    "fit_avg": 9415634035.60873,
                    "fit_max": 1000000000000.0,
                    "fit_min": 54894.53442029445,
                    "fit_std": 96495327607.02377
                },
                {
                    "gen": "15.11",
                    "nevals": 3014,
                    "fit_avg": 8014618357.459767,
                    "fit_max": 1000000000000.0,
                    "fit_min": 54894.53442029445,
                    "fit_std": 89082928103.26741
                },
                {
                    "gen": "15.12",
                    "nevals": 2962,
                    "fit_avg": 9414977592.157497,
                    "fit_max": 1000000000000.0,
                    "fit_min": 54894.53442029445,
                    "fit_std": 96495390446.14394
                },
                {
                    "gen": "15.13",
                    "nevals": 2966,
                    "fit_avg": 11013489134.473444,
                    "fit_max": 1000000000000.0,
                    "fit_min": 54894.53442029445,
                    "fit_std": 104301030878.91708
                },
                {
                    "gen": "15.14",
                    "nevals": 3060,
                    "fit_avg": 9815670403.95568,
                    "fit_max": 1000000000000.0,
                    "fit_min": 54872.1780505024,
                    "fit_std": 98507131357.13666
                },
                {
                    "gen": "15.15",
                    "nevals": 2995,
                    "fit_avg": 8014784198.141539,
                    "fit_max": 1000000000000.0,
                    "fit_min": 54872.1780505024,
                    "fit_std": 89082913013.06691
                }
            ],
            [
                {
                    "gen": "16.0",
                    "nevals": 5000,
                    "fit_avg": 8015236679.371615,
                    "fit_max": 1000000000000.0,
                    "fit_min": 294804.44027082034,
                    "fit_std": 89082872294.24748
                },
                {
                    "gen": "16.1",
                    "nevals": 2934,
                    "fit_avg": 6414374959.190897,
                    "fit_max": 1000000000000.0,
                    "fit_min": 244868.37264212407,
                    "fit_std": 79742446117.86497
                },
                {
                    "gen": "16.2",
                    "nevals": 2932,
                    "fit_avg": 8613160986.310589,
                    "fit_max": 1000000000000.0,
                    "fit_min": 244868.37264212407,
                    "fit_std": 92335341186.2108
                },
                {
                    "gen": "16.3",
                    "nevals": 3002,
                    "fit_avg": 8414797500.423311,
                    "fit_max": 1000000000000.0,
                    "fit_min": 196861.52744789413,
                    "fit_std": 91264414104.8663
                },
                {
                    "gen": "16.4",
                    "nevals": 2958,
                    "fit_avg": 7614400884.689669,
                    "fit_max": 1000000000000.0,
                    "fit_min": 196861.52744789413,
                    "fit_std": 86844820951.11455
                },
                {
                    "gen": "16.5",
                    "nevals": 2960,
                    "fit_avg": 9214616174.66879,
                    "fit_max": 1000000000000.0,
                    "fit_min": 196861.52744789413,
                    "fit_std": 95472995998.9788
                },
                {
                    "gen": "16.6",
                    "nevals": 2886,
                    "fit_avg": 11612934381.596651,
                    "fit_max": 1000000000000.0,
                    "fit_min": 196861.52744789413,
                    "fit_std": 107075400815.81499
                },
                {
                    "gen": "16.7",
                    "nevals": 3037,
                    "fit_avg": 11615909052.004318,
                    "fit_max": 1000000000000.0,
                    "fit_min": 196861.52744789413,
                    "fit_std": 107075080861.04427
                },
                {
                    "gen": "16.8",
                    "nevals": 3070,
                    "fit_avg": 10415913059.210087,
                    "fit_max": 1000000000000.0,
                    "fit_min": 196861.52744789413,
                    "fit_std": 101447085087.90875
                },
                {
                    "gen": "16.9",
                    "nevals": 2976,
                    "fit_avg": 11615569774.028584,
                    "fit_max": 1000000000000.0,
                    "fit_min": 196861.52744789413,
                    "fit_std": 107075118262.00113
                },
                {
                    "gen": "16.10",
                    "nevals": 2991,
                    "fit_avg": 9215955803.056015,
                    "fit_max": 1000000000000.0,
                    "fit_min": 196861.52744789413,
                    "fit_std": 95472868457.12387
                },
                {
                    "gen": "16.11",
                    "nevals": 3006,
                    "fit_avg": 11814571878.096262,
                    "fit_max": 1000000000000.0,
                    "fit_min": 196861.52744789413,
                    "fit_std": 107983415763.89626
                },
                {
                    "gen": "16.12",
                    "nevals": 2888,
                    "fit_avg": 6814169180.97352,
                    "fit_max": 1000000000000.0,
                    "fit_min": 196861.52744789413,
                    "fit_std": 82180102308.94106
                },
                {
                    "gen": "16.13",
                    "nevals": 3046,
                    "fit_avg": 7415826610.046853,
                    "fit_max": 1000000000000.0,
                    "fit_min": 196861.52744789413,
                    "fit_std": 85703021114.36227
                },
                {
                    "gen": "16.14",
                    "nevals": 2943,
                    "fit_avg": 7214767635.418403,
                    "fit_max": 1000000000000.0,
                    "fit_min": 196861.52744789413,
                    "fit_std": 84545544900.39917
                },
                {
                    "gen": "16.15",
                    "nevals": 2937,
                    "fit_avg": 8214177817.89051,
                    "fit_max": 1000000000000.0,
                    "fit_min": 196861.52744789413,
                    "fit_std": 90180537310.07796
                }
            ],
            [
                {
                    "gen": "17.0",
                    "nevals": 5000,
                    "fit_avg": 8214336426.372991,
                    "fit_max": 1000000000000.0,
                    "fit_min": 247130.90000070396,
                    "fit_std": 90180522873.6385
                },
                {
                    "gen": "17.1",
                    "nevals": 2941,
                    "fit_avg": 7814337389.576718,
                    "fit_max": 1000000000000.0,
                    "fit_min": 246280.15509701558,
                    "fit_std": 87971234962.09325
                },
                {
                    "gen": "17.2",
                    "nevals": 3050,
                    "fit_avg": 8415579351.22395,
                    "fit_max": 1000000000000.0,
                    "fit_min": 245993.69547678987,
                    "fit_std": 91264342346.4222
                },
                {
                    "gen": "17.3",
                    "nevals": 3045,
                    "fit_avg": 8013963982.851232,
                    "fit_max": 1000000000000.0,
                    "fit_min": 245981.86172400336,
                    "fit_std": 89082985695.09227
                },
                {
                    "gen": "17.4",
                    "nevals": 2996,
                    "fit_avg": 9213761026.565239,
                    "fit_max": 1000000000000.0,
                    "fit_min": 245803.61335418362,
                    "fit_std": 95473077443.4465
                },
                {
                    "gen": "17.5",
                    "nevals": 3067,
                    "fit_avg": 9414171107.975534,
                    "fit_max": 1000000000000.0,
                    "fit_min": 245803.61335418362,
                    "fit_std": 96495467944.43977
                },
                {
                    "gen": "17.6",
                    "nevals": 2930,
                    "fit_avg": 7812500247.397135,
                    "fit_max": 1000000000000.0,
                    "fit_min": 245798.7584023152,
                    "fit_std": 87971395954.0492
                },
                {
                    "gen": "17.7",
                    "nevals": 3110,
                    "fit_avg": 9812129733.325047,
                    "fit_max": 1000000000000.0,
                    "fit_min": 245798.7584023152,
                    "fit_std": 98507480752.80344
                },
                {
                    "gen": "17.8",
                    "nevals": 3010,
                    "fit_avg": 7212550410.239389,
                    "fit_max": 1000000000000.0,
                    "fit_min": 245703.6925099719,
                    "fit_std": 84545732034.2358
                },
                {
                    "gen": "17.9",
                    "nevals": 2979,
                    "fit_avg": 6811240855.373382,
                    "fit_max": 1000000000000.0,
                    "fit_min": 245703.6925099719,
                    "fit_std": 82180341504.6414
                },
                {
                    "gen": "17.10",
                    "nevals": 2970,
                    "fit_avg": 7012019412.452078,
                    "fit_max": 1000000000000.0,
                    "fit_min": 245703.6925099719,
                    "fit_std": 83371658180.44745
                },
                {
                    "gen": "17.11",
                    "nevals": 3010,
                    "fit_avg": 7411616955.144719,
                    "fit_max": 1000000000000.0,
                    "fit_min": 245558.5738152672,
                    "fit_std": 85703381547.74123
                },
                {
                    "gen": "17.12",
                    "nevals": 2952,
                    "fit_avg": 7409871831.686624,
                    "fit_max": 1000000000000.0,
                    "fit_min": 245558.51531422985,
                    "fit_std": 85703530552.07393
                },
                {
                    "gen": "17.13",
                    "nevals": 2960,
                    "fit_avg": 9811848614.649609,
                    "fit_max": 1000000000000.0,
                    "fit_min": 245558.51531422985,
                    "fit_std": 98507509621.65247
                },
                {
                    "gen": "17.14",
                    "nevals": 2956,
                    "fit_avg": 7812657935.30685,
                    "fit_max": 1000000000000.0,
                    "fit_min": 245558.51531422985,
                    "fit_std": 87971383265.0202
                },
                {
                    "gen": "17.15",
                    "nevals": 2953,
                    "fit_avg": 9613435613.075123,
                    "fit_max": 1000000000000.0,
                    "fit_min": 245558.51531422985,
                    "fit_std": 97506840309.97418
                }
            ],
            [
                {
                    "gen": "18.0",
                    "nevals": 5000,
                    "fit_avg": 9614966906.36376,
                    "fit_max": 1000000000000.0,
                    "fit_min": 699746.568379999,
                    "fit_std": 97506689523.55577
                },
                {
                    "gen": "18.1",
                    "nevals": 2950,
                    "fit_avg": 7613658872.098783,
                    "fit_max": 1000000000000.0,
                    "fit_min": 699746.568379999,
                    "fit_std": 86844885102.84827
                },
                {
                    "gen": "18.2",
                    "nevals": 3104,
                    "fit_avg": 9014048290.426725,
                    "fit_max": 1000000000000.0,
                    "fit_min": 362686.0732598936,
                    "fit_std": 94439127654.67505
                },
                {
                    "gen": "18.3",
                    "nevals": 2964,
                    "fit_avg": 8413385371.685186,
                    "fit_max": 1000000000000.0,
                    "fit_min": 362686.0732598936,
                    "fit_std": 91264542546.7258
                },
                {
                    "gen": "18.4",
                    "nevals": 3084,
                    "fit_avg": 7014601994.300743,
                    "fit_max": 1000000000000.0,
                    "fit_min": 119508.36640926576,
                    "fit_std": 83371442683.5941
                },
                {
                    "gen": "18.5",
                    "nevals": 3005,
                    "fit_avg": 8215653452.5896435,
                    "fit_max": 1000000000000.0,
                    "fit_min": 119508.36640926576,
                    "fit_std": 90180404413.70287
                },
                {
                    "gen": "18.6",
                    "nevals": 2939,
                    "fit_avg": 8614483391.005056,
                    "fit_max": 1000000000000.0,
                    "fit_min": 119508.36640926576,
                    "fit_std": 92335219661.01479
                },
                {
                    "gen": "18.7",
                    "nevals": 2904,
                    "fit_avg": 7416372480.58571,
                    "fit_max": 1000000000000.0,
                    "fit_min": 118056.10794649023,
                    "fit_std": 85702975175.75641
                },
                {
                    "gen": "18.8",
                    "nevals": 2917,
                    "fit_avg": 8416306265.5014,
                    "fit_max": 1000000000000.0,
                    "fit_min": 118056.10794649023,
                    "fit_std": 91264277684.54585
                },
                {
                    "gen": "18.9",
                    "nevals": 2931,
                    "fit_avg": 9214748690.181515,
                    "fit_max": 1000000000000.0,
                    "fit_min": 118056.10794649023,
                    "fit_std": 95472984217.58736
                },
                {
                    "gen": "18.10",
                    "nevals": 3018,
                    "fit_avg": 9415029751.058304,
                    "fit_max": 1000000000000.0,
                    "fit_min": 118056.10794649023,
                    "fit_std": 96495387492.69514
                },
                {
                    "gen": "18.11",
                    "nevals": 3013,
                    "fit_avg": 6415771093.440678,
                    "fit_max": 1000000000000.0,
                    "fit_min": 117845.38408981646,
                    "fit_std": 79742337921.01343
                },
                {
                    "gen": "18.12",
                    "nevals": 3027,
                    "fit_avg": 10412996014.930368,
                    "fit_max": 1000000000000.0,
                    "fit_min": 118056.10794649023,
                    "fit_std": 101447383015.88947
                },
                {
                    "gen": "18.13",
                    "nevals": 3008,
                    "fit_avg": 7611672746.357434,
                    "fit_max": 1000000000000.0,
                    "fit_min": 117134.68587326433,
                    "fit_std": 86845057813.88402
                },
                {
                    "gen": "18.14",
                    "nevals": 3004,
                    "fit_avg": 9809912556.842213,
                    "fit_max": 1000000000000.0,
                    "fit_min": 117134.68587326433,
                    "fit_std": 98507700200.31737
                },
                {
                    "gen": "18.15",
                    "nevals": 3052,
                    "fit_avg": 10610448256.348507,
                    "fit_max": 1000000000000.0,
                    "fit_min": 117134.68587326433,
                    "fit_std": 102408104506.04378
                }
            ],
            [
                {
                    "gen": "19.0",
                    "nevals": 5000,
                    "fit_avg": 10610578262.37232,
                    "fit_max": 1000000000000.0,
                    "fit_min": 244754.06166573553,
                    "fit_std": 102408090980.02615
                },
                {
                    "gen": "19.1",
                    "nevals": 3026,
                    "fit_avg": 10809321538.053085,
                    "fit_max": 1000000000000.0,
                    "fit_min": 244754.06166573553,
                    "fit_std": 103359372118.11772
                },
                {
                    "gen": "19.2",
                    "nevals": 3057,
                    "fit_avg": 8009654846.214436,
                    "fit_max": 1000000000000.0,
                    "fit_min": 244754.06166573553,
                    "fit_std": 89083369495.66463
                },
                {
                    "gen": "19.3",
                    "nevals": 3008,
                    "fit_avg": 10408885427.285757,
                    "fit_max": 1000000000000.0,
                    "fit_min": 244754.06166573553,
                    "fit_std": 101447800834.81401
                },
                {
                    "gen": "19.4",
                    "nevals": 3017,
                    "fit_avg": 7809667196.279238,
                    "fit_max": 1000000000000.0,
                    "fit_min": 244754.06166573553,
                    "fit_std": 87971645704.39238
                },
                {
                    "gen": "19.5",
                    "nevals": 2940,
                    "fit_avg": 8010405027.321766,
                    "fit_max": 1000000000000.0,
                    "fit_min": 244754.06166573553,
                    "fit_std": 89083303505.49686
                },
                {
                    "gen": "19.6",
                    "nevals": 3002,
                    "fit_avg": 9210068724.21806,
                    "fit_max": 1000000000000.0,
                    "fit_min": 242524.7726208862,
                    "fit_std": 95473431048.49663
                },
                {
                    "gen": "19.7",
                    "nevals": 3053,
                    "fit_avg": 8610041796.199257,
                    "fit_max": 1000000000000.0,
                    "fit_min": 242524.7726208862,
                    "fit_std": 92335629878.44203
                },
                {
                    "gen": "19.8",
                    "nevals": 3055,
                    "fit_avg": 9810505755.134686,
                    "fit_max": 1000000000000.0,
                    "fit_min": 148938.08036919517,
                    "fit_std": 98507641444.09282
                },
                {
                    "gen": "19.9",
                    "nevals": 3015,
                    "fit_avg": 7212862796.948594,
                    "fit_max": 1000000000000.0,
                    "fit_min": 148938.08036919517,
                    "fit_std": 84545705901.85538
                },
                {
                    "gen": "19.10",
                    "nevals": 2915,
                    "fit_avg": 8615021764.250637,
                    "fit_max": 1000000000000.0,
                    "fit_min": 146210.96925680348,
                    "fit_std": 92335169764.65388
                },
                {
                    "gen": "19.11",
                    "nevals": 2868,
                    "fit_avg": 8013263582.889272,
                    "fit_max": 1000000000000.0,
                    "fit_min": 146210.96925680348,
                    "fit_std": 89083048205.01672
                },
                {
                    "gen": "19.12",
                    "nevals": 2999,
                    "fit_avg": 8614015578.792137,
                    "fit_max": 1000000000000.0,
                    "fit_min": 146210.96925680348,
                    "fit_std": 92335262596.64026
                },
                {
                    "gen": "19.13",
                    "nevals": 2982,
                    "fit_avg": 11014906277.848286,
                    "fit_max": 1000000000000.0,
                    "fit_min": 146210.96925680348,
                    "fit_std": 104300882171.5089
                },
                {
                    "gen": "19.14",
                    "nevals": 3051,
                    "fit_avg": 8814712959.401892,
                    "fit_max": 1000000000000.0,
                    "fit_min": 146210.96925680348,
                    "fit_std": 93393270619.90501
                },
                {
                    "gen": "19.15",
                    "nevals": 3026,
                    "fit_avg": 9213168346.003857,
                    "fit_max": 1000000000000.0,
                    "fit_min": 146210.96925680348,
                    "fit_std": 95473134647.24232
                }
            ],
            [
                {
                    "gen": "20.0",
                    "nevals": 5000,
                    "fit_avg": 9213277614.995659,
                    "fit_max": 1000000000000.0,
                    "fit_min": 183414.82186232007,
                    "fit_std": 95473124082.51521
                },
                {
                    "gen": "20.1",
                    "nevals": 3045,
                    "fit_avg": 9411010282.456024,
                    "fit_max": 1000000000000.0,
                    "fit_min": 183414.82186232007,
                    "fit_std": 96495775066.93394
                },
                {
                    "gen": "20.2",
                    "nevals": 2991,
                    "fit_avg": 7610573515.100147,
                    "fit_max": 1000000000000.0,
                    "fit_min": 181635.54844505366,
                    "fit_std": 86845154874.07426
                },
                {
                    "gen": "20.3",
                    "nevals": 3030,
                    "fit_avg": 5410975770.505412,
                    "fit_max": 1000000000000.0,
                    "fit_min": 181635.54844505366,
                    "fit_std": 73285217752.32237
                },
                {
                    "gen": "20.4",
                    "nevals": 3036,
                    "fit_avg": 8610966331.7945,
                    "fit_max": 1000000000000.0,
                    "fit_min": 181635.54844505366,
                    "fit_std": 92335545851.7798
                },
                {
                    "gen": "20.5",
                    "nevals": 3131,
                    "fit_avg": 11612513227.346663,
                    "fit_max": 1000000000000.0,
                    "fit_min": 181635.54844505366,
                    "fit_std": 107075448049.19162
                },
                {
                    "gen": "20.6",
                    "nevals": 3080,
                    "fit_avg": 10014306938.169554,
                    "fit_max": 1000000000000.0,
                    "fit_min": 181635.54844505366,
                    "fit_std": 99497316617.49973
                },
                {
                    "gen": "20.7",
                    "nevals": 3004,
                    "fit_avg": 8014474981.261756,
                    "fit_max": 1000000000000.0,
                    "fit_min": 181467.05018809863,
                    "fit_std": 89082942117.49733
                },
                {
                    "gen": "20.8",
                    "nevals": 2977,
                    "fit_avg": 7415563468.884127,
                    "fit_max": 1000000000000.0,
                    "fit_min": 181467.05018809863,
                    "fit_std": 85703044756.20988
                },
                {
                    "gen": "20.9",
                    "nevals": 3083,
                    "fit_avg": 10015287117.9813,
                    "fit_max": 1000000000000.0,
                    "fit_min": 181467.05018809863,
                    "fit_std": 99497218421.59799
                },
                {
                    "gen": "20.10",
                    "nevals": 2988,
                    "fit_avg": 8413898498.34378,
                    "fit_max": 1000000000000.0,
                    "fit_min": 181467.05018809863,
                    "fit_std": 91264497769.98105
                },
                {
                    "gen": "20.11",
                    "nevals": 3020,
                    "fit_avg": 7813912247.082039,
                    "fit_max": 1000000000000.0,
                    "fit_min": 181467.05018809863,
                    "fit_std": 87971274388.75919
                },
                {
                    "gen": "20.12",
                    "nevals": 2975,
                    "fit_avg": 8413313028.4248,
                    "fit_max": 1000000000000.0,
                    "fit_min": 181467.05018809863,
                    "fit_std": 91264551461.28966
                },
                {
                    "gen": "20.13",
                    "nevals": 2951,
                    "fit_avg": 7212931824.68134,
                    "fit_max": 1000000000000.0,
                    "fit_min": 181380.68029349938,
                    "fit_std": 84545701948.04692
                },
                {
                    "gen": "20.14",
                    "nevals": 2966,
                    "fit_avg": 7013351925.9024315,
                    "fit_max": 1000000000000.0,
                    "fit_min": 181380.68029349938,
                    "fit_std": 83371548039.70035
                },
                {
                    "gen": "20.15",
                    "nevals": 3092,
                    "fit_avg": 10615234510.353987,
                    "fit_max": 1000000000000.0,
                    "fit_min": 181131.24508436912,
                    "fit_std": 102407613496.04698
                }
            ]
        ]
    }
]